json_to_ubl_xml_transformer/__init__.py
json_to_ubl_xml_transformer/cli.py
json_to_ubl_xml_transformer/constants.py
json_to_ubl_xml_transformer/json_to_ubl_xml_transformer.py
json_to_ubl_xml_transformer/transformers.py
json_to_ubl_xml_transformer/utils.py
json_to_ubl_xml_transformer-0.2.1.dist-info/AUTHORS.rst
json_to_ubl_xml_transformer-0.2.1.dist-info/LICENSE
json_to_ubl_xml_transformer-0.2.1.dist-info/METADATA
json_to_ubl_xml_transformer-0.2.1.dist-info/WHEEL
json_to_ubl_xml_transformer-0.2.1.dist-info/entry_points.txt
json_to_ubl_xml_transformer-0.2.1.dist-info/top_level.txt
json_to_ubl_xml_transformer-0.2.1.dist-info/RECORD
