Metadata-Version: 2.1
Name: json-to-ubl-xml-transformer
Version: 0.2.1
Summary: Converts JSON input files to PEPPOL BIS 3.0 Invoice UBL XML outputs and validates them
Home-page: https://github.com/dimitern/json_to_ubl_xml_transformer
Author: Dimiter Naydenov
Author-email: dimiter@naydenov.net
License: MIT license
Keywords: json_to_ubl_xml_transformer
Platform: UNKNOWN
Classifier: Development Status :: 2 - Pre-Alpha
Classifier: Intended Audience :: Developers
Classifier: License :: OSI Approved :: MIT License
Classifier: Natural Language :: English
Classifier: Programming Language :: Python :: 2
Classifier: Programming Language :: Python :: 2.7
Classifier: Programming Language :: Python :: 3
Classifier: Programming Language :: Python :: 3.5
Classifier: Programming Language :: Python :: 3.6
Classifier: Programming Language :: Python :: 3.7
Classifier: Programming Language :: Python :: 3.8
Requires-Dist: Click (>=6.0)
